LICENSE
MANIFEST.in
README.md
setup.cfg
setup.py
sublimedsl/__init__.py
sublimedsl/keymap.py
sublimedsl.egg-info/PKG-INFO
sublimedsl.egg-info/SOURCES.txt
sublimedsl.egg-info/dependency_links.txt
sublimedsl.egg-info/requires.txt
sublimedsl.egg-info/top_level.txt