Metadata-Version: 1.1
Name: sublimedsl
Version: 0.3.2
Summary: A convenient DSL for generating SublimeText configs.
Home-page: https://github.com/jirutka/sublimedsl
Author: Jakub Jirutka
Author-email: jakub@jirutka.cz
License: MIT
Platform: UNKNOWN
Classifier: Intended Audience :: Developers
Classifier: License :: OSI Approved :: MIT License
Classifier: Programming Language :: Python :: 3
Classifier: Topic :: Utilities
